{"index": {"version":"0.7.0","fields":[{"name":"title","boost":100}],"ref":"id","tokenizer":"default","documentStore":{"store":{"1":["help","rail","rubi","start"],"2":["titl"],"3":["aider","démarrer","pour","rail","rubi","vou"],"4":["le","novic","pour","rail","rubi"],"29":["beginn","rail","rubi"]},"length":5},"tokenStore":{"root":{"docs":{},"h":{"docs":{},"e":{"docs":{},"l":{"docs":{},"p":{"docs":{"1":{"ref":1,"tf":25}}}}}},"r":{"docs":{},"a":{"docs":{},"i":{"docs":{},"l":{"docs":{"1":{"ref":1,"tf":25},"3":{"ref":3,"tf":16.666666666666664},"4":{"ref":4,"tf":20},"29":{"ref":29,"tf":33.33333333333333}}}}},"u":{"docs":{},"b":{"docs":{},"i":{"docs":{"1":{"ref":1,"tf":25},"3":{"ref":3,"tf":16.666666666666664},"4":{"ref":4,"tf":20},"29":{"ref":29,"tf":33.33333333333333}}}}}},"s":{"docs":{},"t":{"docs":{},"a":{"docs":{},"r":{"docs":{},"t":{"docs":{"1":{"ref":1,"tf":25}}}}}}},"t":{"docs":{},"i":{"docs":{},"t":{"docs":{},"l":{"docs":{"2":{"ref":2,"tf":100}}}}}},"a":{"docs":{},"i":{"docs":{},"d":{"docs":{},"e":{"docs":{},"r":{"docs":{"3":{"ref":3,"tf":16.666666666666664}}}}}}},"d":{"docs":{},"é":{"docs":{},"m":{"docs":{},"a":{"docs":{},"r":{"docs":{},"r":{"docs":{},"e":{"docs":{},"r":{"docs":{"3":{"ref":3,"tf":16.666666666666664}}}}}}}}}},"p":{"docs":{},"o":{"docs":{},"u":{"docs":{},"r":{"docs":{"3":{"ref":3,"tf":16.666666666666664},"4":{"ref":4,"tf":20}}}}}},"v":{"docs":{},"o":{"docs":{},"u":{"docs":{"3":{"ref":3,"tf":16.666666666666664}}}}},"l":{"docs":{},"e":{"docs":{"4":{"ref":4,"tf":20}}}},"n":{"docs":{},"o":{"docs":{},"v":{"docs":{},"i":{"docs":{},"c":{"docs":{"4":{"ref":4,"tf":20}}}}}}},"b":{"docs":{},"e":{"docs":{},"g":{"docs":{},"i":{"docs":{},"n":{"docs":{},"n":{"docs":{"29":{"ref":29,"tf":33.33333333333333}}}}}}}}},"length":19},"corpusTokens":["aider","beginn","démarrer","help","le","novic","pour","rail","rubi","start","titl","vou"],"pipeline":["trimmer","stopWordFilter","stemmer"]}, "docs": {"1":{"title":"Ruby on Rails can help you get started","date":"2017-07-11 18:14 BST","url":"/blog/en/2017/07/11/rubyonrails-can-help-you-get-started/","group":"blog"},"2":{"title":"<%= @title %>","date":"<%= @date.strftime('%F %R %Z') %>","url":"/blog/en/blog-article-template","group":"blog"},"3":{"title":"Ruby on Rails pour vous aider à démarrer","date":"2017-07-11 18:14 BST","url":"/blog/fr/2017/07/11/ruby-on-rails-can-help-you-get-started/","group":"blog"},"4":{"title":"Ruby on Rails pour les novices","date":"2017-07-11 18:12 BST","url":"/blog/fr/2017/07/11/ruby-on-rails-for-beginners/","group":"blog"},"29":{"title":"Ruby on Rails for Beginners","date":"2017-07-11 18:12 BST","url":"/blog/en/2017/07/11/ruby-on-rails-for-beginners/","group":"blog"}}}